telebaka_robot/__init__.py
telebaka_robot/admin.py
telebaka_robot/bot.py
telebaka_robot/models.py
telebaka_robot/preferences.py
telebaka_robot/migrations/0001_initial.py
telebaka_robot/migrations/__init__.py
telebaka_robot-0.1.7.dist-info/METADATA
telebaka_robot-0.1.7.dist-info/RECORD
telebaka_robot-0.1.7.dist-info/WHEEL
telebaka_robot-0.1.7.dist-info/top_level.txt
