Metadata-Version: 2.1
Name: telebaka-robot
Version: 0.1.7
Summary: UNKNOWN
Home-page: UNKNOWN
Author: bakatrouble
Author-email: bakatrouble@gmail.com
License: UNKNOWN
Platform: UNKNOWN
Requires-Dist: django
Requires-Dist: python-telegram-bot
Requires-Dist: requests
Requires-Dist: django-dynamic-preferences
